{"cameraMode":{"drawMode":0,"name":"Shaded","section":"Shading Mode"},"sceneLighting":true,"audioPlay":false,"sceneViewState":{"m_AlwaysRefresh":false,"showFog":true,"showSkybox":true,"showFlares":true,"showImageEffects":true,"showParticleSystems":true,"showVisualEffectGraphs":true,"m_FxEnabled":true},"in2DMode":false,"pivot":{"x":-1.4096221923828126,"y":20.54958152770996,"z":2.5363235473632814},"rotation":{"x":-0.18831954896450044,"y":0.740759551525116,"z":-0.23183198273181916,"w":-0.6017220616340637},"size":13.509793281555176,"orthographic":false}